<?xml version="1.0" encoding="UTF-8"?>
<objects serializationModel="Studio.02.02.00">
	<object class="AudioFile" id="{8a25750d-aca6-4b42-8555-73498588f7b0}">
		<property name="assetPath">
			<value>Music/break room.wav</value>
		</property>
		<property name="isStreaming">
			<value>true</value>
		</property>
		<property name="frequencyInKHz">
			<value>44.0999985</value>
		</property>
		<property name="channelCount">
			<value>2</value>
		</property>
		<property name="length">
			<value>32.453650793650795</value>
		</property>
		<relationship name="masterAssetFolder">
			<destination>{c30e2131-0b4a-4702-b58d-56c275f7a241}</destination>
		</relationship>
	</object>
</objects>
